{
  "category": "tajuk utama",
  "gold_labels": [
    [false, true],
    [true],
    [false],
    [true, true],
    [false],
    [false, false],
    [false, false],
    [false],
    [false, false],
    [false]
  ],
  "id": "1515789000-program-ok-oce-kurang-sosialisasi",
  "paragraphs": [
    [
      ["Suara.com", "-", "kurang", "sosialisasi", "."],
      [
        "Banyak",
        "masyarakat",
        "yang",
        "kurang",
        "faham",
        "dengan",
        "program",
        "ini",
        "."
      ]
    ],
    [
      [
        "Ia",
        "mengatakan",
        "sebaiknya",
        "program",
        "ini",
        "harus",
        "lebih",
        "banyak",
        "disosialisasikan",
        "lagi",
        "."
      ]
    ],
    [
      [
        "\"",
        "Jadi",
        "mungkin",
        "kekurangan",
        "dari",
        "program",
        "ini",
        "adalah",
        "dari",
        "segi",
        "sosialisasi",
        "tersebut",
        "jadi",
        "masyarakat",
        "Cuma",
        "tahu",
        "ujungnya",
        "saja",
        ",",
        "tidak",
        "tahu",
        "rencana",
        "dan",
        "maksud",
        "tujuan",
        "program",
        "ini",
        "bagusnya",
        "untuk",
        "apa",
        ",",
        "\u201d",
        "katanya",
        "."
      ]
    ],
    [
      [
        "Namun",
        "minat",
        "masyarakat",
        "untuk",
        "ikut",
        "bergabung",
        "semakin",
        "besar",
        "."
      ],
      [
        "Program",
        "ini",
        ",",
        "bagi",
        "Herlin",
        "merupakan",
        "program",
        "yang",
        "bagus",
        "karena",
        "membina",
        "enterpreneur",
        "yang",
        "masih",
        "baru",
        "untuk",
        "lebih",
        "awear",
        "dengan",
        "bagaimana",
        "cara",
        "marketing",
        "dan",
        "membuat",
        "keuangan",
        "yang",
        "benar",
        "."
      ]
    ],
    [["Baca_Juga"]],
    [
      [
        "Sementara",
        "itu",
        ",",
        "anggota",
        "komunitas",
        "Pergerakan",
        "Ok",
        "Oce",
        "yang",
        "lain",
        ",",
        "Imam",
        "Pesuwaryantoro",
        "(",
        "26",
        ")",
        "berharap",
        "agar",
        "program",
        "Ok",
        "Oce",
        "ini",
        "segera",
        "berjalan",
        "karena",
        "banyak",
        "sekali",
        "masyarakat",
        "dan",
        "teman-teman",
        "dari",
        "komunitas",
        "sudah",
        "menunggu",
        "."
      ],
      [
        "Menurutnya",
        "Program",
        "tersebut",
        "jika",
        "dijalankan",
        "lebih",
        "cepat",
        "maka",
        "akan",
        "semakin",
        "baik",
        "."
      ]
    ],
    [
      [
        "Imam",
        "mengatakan",
        "alasannya",
        "ikut",
        "bergabung",
        "dalam",
        "Pergerakan",
        "Ok",
        "Oce",
        "ingin",
        "turut",
        "berperan",
        "dalam",
        "meningkatkan",
        "perekonomian",
        "negara",
        "dengan",
        "cara",
        "wirausaha",
        "."
      ],
      [
        "Program",
        "Ok",
        "oce",
        "merupakan",
        "gagasan",
        "yang",
        "tepat",
        "untuk",
        "meningkatkan",
        "daya",
        "saing",
        "dan",
        "daya",
        "wirausaha",
        "baik",
        "tingkat",
        "lokal",
        "maupun",
        "daerah",
        "."
      ]
    ],
    [
      [
        "\u201c",
        "Di",
        "dalam",
        "program",
        "SME",
        "ini",
        "pun",
        "kami",
        "para",
        "wirausaha",
        "-",
        "wirausaha",
        "lokal",
        "mampu",
        "menyetarakan",
        "pengusaha",
        "ekspor",
        ",",
        "\u201d",
        "katanya",
        "."
      ]
    ],
    [
      [
        "Selain",
        "itu",
        ",",
        "program",
        "itu",
        "akan",
        "lebih",
        "baik",
        "bula",
        "dilakukan",
        "secara",
        "kongkrit",
        "dan",
        "berkala",
        "."
      ],
      [
        "Jadi",
        "harus",
        "ada",
        "evaluasi",
        "bila",
        "ada",
        "kekurangan",
        "atau",
        "tiap",
        "progress",
        "yang",
        "sudah",
        "dilakukan",
        "."
      ]
    ],
    [
      [
        "\u201c",
        "Pelatihan",
        "saja",
        "tidak",
        "cukup",
        "kalau",
        "bisa",
        "pakai",
        "akses",
        "permodalan",
        "atau",
        "dengan",
        "skema",
        "bagi",
        "hasil",
        ",",
        "\u201d",
        "pungkasnya",
        "."
      ]
    ]
  ],
  "source": "suara",
  "source_url": "https://www.suara.com/news/2018/01/12/050000/program-ok-oce-kurang-sosialisasi",
  "summary": [
    [
      "Salah",
      "seorang",
      "anggota",
      "komunitas",
      "Pergerakan",
      "OK",
      "OCE",
      "\u00a0 ",
      "Herlin",
      "Syahrita",
      "(",
      "29",
      ")",
      "menilai",
      "Program",
      "OK",
      "OCE",
      "kurang",
      "sosialisasi",
      "."
    ],
    [
      "Banyak",
      "masyarakat",
      "yang",
      "kurang",
      "faham",
      "dengan",
      "program",
      "ini",
      "."
    ],
    [
      "Ia",
      "mengatakan",
      "sebaiknya",
      "program",
      "ini",
      "harus",
      "lebih",
      "banyak",
      "disosialisasikan",
      "lagi",
      "."
    ],
    [
      "Namun",
      "minat",
      "masyarakat",
      "untuk",
      "ikut",
      "bergabung",
      "semakin",
      "besar",
      "."
    ],
    [
      "Program",
      "ini",
      ",",
      "bagi",
      "Herlin",
      "merupakan",
      "program",
      "yang",
      "bagus",
      "karena",
      "membina",
      "pengusaha",
      "yang",
      "masih",
      "baru",
      "."
    ]
  ]
}
